pretext/__init__.py
pretext/__main__.py
pretext/build.py
pretext/cli.py
pretext/core/__init__.py
pretext/core/pretext.py
pretext/core/resources.py
pretext/core/resources.zip
pretext/generate.py
pretext/project.py
pretext/templates/__init__.py
pretext/templates/resources/.gitignore
pretext/templates/resources/__init__.py
pretext/templates/resources/article.zip
pretext/templates/resources/book.zip
pretext/templates/resources/hello.zip
pretext/templates/resources/project.ptx
pretext/templates/resources/publication.ptx
pretext/templates/resources/slideshow.zip
pretext/utils.py
pretextbook-0.8.3.dist-info/entry_points.txt
pretextbook-0.8.3.dist-info/LICENSE
pretextbook-0.8.3.dist-info/WHEEL
pretextbook-0.8.3.dist-info/METADATA
pretextbook-0.8.3.dist-info/RECORD
