Metadata-Version: 2.1
Name: pretextbook
Version: 0.8.3
Summary: A package to author, build, and deploy PreTeXt projects.
License: GPL-3.0-or-later
Author: PreTeXtBook.org
Author-email: steven.clontz+PreTeXt@gmail.com
Requires-Python: >=3.8.5,<4.0.0
Classifier: License :: OSI Approved :: GNU General Public License v3 or later (GPLv3+)
Classifier: Programming Language :: Python :: 3
Classifier: Programming Language :: Python :: 3.10
Classifier: Programming Language :: Python :: 3.9
Requires-Dist: CodeChat-Server (>=0.2.6,<0.3.0)
Requires-Dist: GitPython (>=3,<4)
Requires-Dist: PyPDF2 (>=2.5,<2.6)
Requires-Dist: click (>=8,<9)
Requires-Dist: click-log (>=0.4,<0.5)
Requires-Dist: ghp-import (>=2,<3)
Requires-Dist: lxml (>=4.8,<5.0)
Requires-Dist: pdfCropMargins (>=1.0.9,<1.1.0)
Requires-Dist: pyppeteer (>=1.0.2,<2.0.0)
Requires-Dist: requests (>=2,<3)
Requires-Dist: single-version (>=1,<2)
Requires-Dist: watchdog (>=2,<3)
